fakexy/__init__.py
fakexy/__main__.py
fakexy/cli.py
fakexy/fakexy.py
fakexy-0.0.2.dist-info/licenses/LICENSE
fakexy-0.0.2.dist-info/METADATA
fakexy-0.0.2.dist-info/WHEEL
fakexy-0.0.2.dist-info/entry_points.txt
fakexy-0.0.2.dist-info/top_level.txt
fakexy-0.0.2.dist-info/RECORD
