Metadata-Version: 2.4
Name: fakexy
Version: 0.0.2
Summary: A simple scraper for fakexy.com
Author-email: Dominik Stanisław Suchora <hexderm@gmail.com>
License: GPLv3
Project-URL: Homepage, https://github.com/TUVIMEN/fakexy
Keywords: fake-data,scraper,api,fakexy
Classifier: Development Status :: 5 - Production/Stable
Classifier: License :: OSI Approved :: GNU General Public License v3 (GPLv3)
Classifier: Operating System :: OS Independent
Classifier: Programming Language :: Python :: 3
Classifier: Programming Language :: Python :: 3.8
Classifier: Programming Language :: Python :: 3.9
Classifier: Programming Language :: Python :: 3.10
Classifier: Programming Language :: Python :: 3.11
Classifier: Programming Language :: Python :: 3.12
Classifier: Programming Language :: Python :: 3.13
Classifier: Programming Language :: Python :: 3 :: Only
Requires-Python: >=3.8
License-File: LICENSE
Requires-Dist: requests
Requires-Dist: reliq
Requires-Dist: treerequests
Dynamic: license-file
